polidoro_terminal/__init__.py
polidoro_terminal/color.py
polidoro_terminal/cursor.py
polidoro_terminal/format.py
polidoro_terminal/getch.py
polidoro_terminal/manipulation.py
polidoro_terminal/size.py
polidoro_terminal-1.0.0.dist-info/LICENSE
polidoro_terminal-1.0.0.dist-info/METADATA
polidoro_terminal-1.0.0.dist-info/WHEEL
polidoro_terminal-1.0.0.dist-info/top_level.txt
polidoro_terminal-1.0.0.dist-info/RECORD
