Metadata-Version: 2.1
Name: polidoro-terminal
Version: 1.0.0
Summary: Terminal Terminal.
Home-page: https://github.com/heitorpolidoro/polidoro-terminal
Author: Heitor Polidoro
License: unlicense
Platform: UNKNOWN
Classifier: Programming Language :: Python :: 3
Classifier: License :: OSI Approved :: MIT License
Classifier: Operating System :: OS Independent
License-File: LICENSE
